memnet/__init__.py
memnet/mapping.py
memnet/nonidealities.py
memnet/utils.py
memnet-0.0.1.dist-info/LICENSE
memnet-0.0.1.dist-info/METADATA
memnet-0.0.1.dist-info/WHEEL
memnet-0.0.1.dist-info/top_level.txt
memnet-0.0.1.dist-info/RECORD
